filehandlers/__init__.py
filehandlers-3.1.0.dist-info/LICENSE
filehandlers-3.1.0.dist-info/METADATA
filehandlers-3.1.0.dist-info/WHEEL
filehandlers-3.1.0.dist-info/top_level.txt
filehandlers-3.1.0.dist-info/RECORD
