Metadata-Version: 2.1
Name: filehandlers
Version: 3.1.0
Summary: Package containing code to help in working with files.
Home-page: https://github.com/RDIL/filehandlers
Author: Reece Dunham
Author-email: me@rdil.rocks
License: MIT
Project-URL: Documentation, https://docs.rdil.rocks/libraries/filehandlers/
Project-URL: Source Code, https://github.com/RDIL/filehandlers
Project-URL: Bug Tracker, https://github.com/RDIL/filehandlers/issues
Keywords: file,files,handler,handlers,io
Platform: UNKNOWN
Classifier: Development Status :: 5 - Production/Stable
Classifier: Intended Audience :: Developers
Classifier: Intended Audience :: Information Technology
Classifier: License :: OSI Approved :: MIT License
Classifier: Natural Language :: English
Classifier: Operating System :: MacOS
Classifier: Operating System :: Microsoft :: Windows
Classifier: Operating System :: Unix
Classifier: Operating System :: POSIX
Classifier: Programming Language :: Python :: 3
Classifier: Programming Language :: Python :: 3 :: Only
Classifier: Programming Language :: Python :: 3.6
Classifier: Programming Language :: Python :: 3.7
Classifier: Programming Language :: Python :: 3.8
Classifier: Programming Language :: Python :: 3.9
Classifier: Topic :: System :: Filesystems
Classifier: Topic :: Utilities
Classifier: Typing :: Typed
Requires-Python: >=3.3
